odoo/addons/ssi_data_requirement_mixin/README.rst
odoo/addons/ssi_data_requirement_mixin/__init__.py
odoo/addons/ssi_data_requirement_mixin/__manifest__.py
odoo/addons/ssi_data_requirement_mixin/menu.xml
odoo/addons/ssi_data_requirement_mixin/data/approval_template_data.xml
odoo/addons/ssi_data_requirement_mixin/data/ir_sequence_data.xml
odoo/addons/ssi_data_requirement_mixin/data/policy_template_data.xml
odoo/addons/ssi_data_requirement_mixin/data/sequence_template_data.xml
odoo/addons/ssi_data_requirement_mixin/i18n/ssi_data_requirement_mixin.pot
odoo/addons/ssi_data_requirement_mixin/models/__init__.py
odoo/addons/ssi_data_requirement_mixin/models/data_requirement.py
odoo/addons/ssi_data_requirement_mixin/models/data_requirement_configurator.py
odoo/addons/ssi_data_requirement_mixin/models/data_requirement_package.py
odoo/addons/ssi_data_requirement_mixin/models/data_requirement_package_detail.py
odoo/addons/ssi_data_requirement_mixin/models/data_requirement_package_type.py
odoo/addons/ssi_data_requirement_mixin/models/data_requirement_package_type_detail.py
odoo/addons/ssi_data_requirement_mixin/models/data_requirement_type.py
odoo/addons/ssi_data_requirement_mixin/models/data_requirement_type_category.py
odoo/addons/ssi_data_requirement_mixin/models/mixin_data_requirement.py
odoo/addons/ssi_data_requirement_mixin/models/mixin_data_requirement_configurator.py
odoo/addons/ssi_data_requirement_mixin/security/ir.model.access.csv
odoo/addons/ssi_data_requirement_mixin/security/ir_module_category_data.xml
odoo/addons/ssi_data_requirement_mixin/security/ir_rule_data.xml
odoo/addons/ssi_data_requirement_mixin/security/res_group_data.xml
odoo/addons/ssi_data_requirement_mixin/static/description/icon.png
odoo/addons/ssi_data_requirement_mixin/templates/mixin_data_requirement_templates.xml
odoo/addons/ssi_data_requirement_mixin/views/data_requirement_package_type_views.xml
odoo/addons/ssi_data_requirement_mixin/views/data_requirement_package_views.xml
odoo14_addon_ssi_data_requirement_mixin-14.0.3.8.0.dist-info/METADATA
odoo14_addon_ssi_data_requirement_mixin-14.0.3.8.0.dist-info/WHEEL
odoo14_addon_ssi_data_requirement_mixin-14.0.3.8.0.dist-info/top_level.txt
odoo14_addon_ssi_data_requirement_mixin-14.0.3.8.0.dist-info/RECORD
